<?xml version="1.0" encoding="utf-8" ?>
<dwsync>
<file name="CemListMonroeTN.php" local="128569431000000000" remote="128569431000000000" testing="0" />
<file name="CivilWargenlinks.php" local="128569431000000000" remote="128569431000000000" testing="0" />
<file name="Georgiagenlinks.php" local="128569431000000000" remote="128569431000000000" testing="0" />
<file name="Germangenlinks.php" local="128569431000000000" remote="128569431000000000" testing="0" />
<file name="Lutherangenlinks.php" local="128569431600000000" remote="128569431600000000" testing="0" />
<file name="Missgenlinks.php" local="128569431600000000" remote="128569431600000000" testing="0" />
<file name="Montanagenlinks.php" local="128569431600000000" remote="128569431600000000" testing="0" />
<file name="NMexgenlinks.php" local="128569431600000000" remote="128569431600000000" testing="0" />
<file name="OKgenlinks.php" local="128569431600000000" remote="128569431600000000" testing="0" />
<file name="PacNWgenlinks.php" local="128569431600000000" remote="128569431600000000" testing="0" />
<file name="Wisgenlinks.php" local="128569431600000000" remote="128569431600000000" testing="0" />
<file name="aframergenlinks.php" local="128569431000000000" remote="128569431000000000" testing="0" />
<file name="algenlinks.php" local="128569431000000000" remote="128569431000000000" testing="0" />
<file name="argenlinks.php" local="128569431000000000" remote="128569431000000000" testing="0" />
<file name="azgenlinks.php" local="128569431000000000" remote="128569431000000000" testing="0" />
<file name="cngenlinks.php" local="128569431000000000" remote="128569431000000000" testing="0" />
<file name="default.htm" local="128569431000000000" remote="128569431000000000" testing="0" />
<file name="degenlinks.php" local="128569431000000000" remote="128569431000000000" testing="0" />
<file name="flgenlinks.php" local="128569431000000000" remote="128569431000000000" testing="0" />
<file name="hagenlinks.php" local="128569431000000000" remote="128569431000000000" testing="0" />
<file name="ilgenlinks.php" local="128569431000000000" remote="128569431000000000" testing="0" />
<file name="ingenlinks.php" local="128569431000000000" remote="128569431000000000" testing="0" />
<file name="iogenlinks.php" local="128569431000000000" remote="128569431000000000" testing="0" />
<file name="ksgenlinks.php" local="128569431000000000" remote="128569431000000000" testing="0" />
<file name="kygenlinks.php" local="128569431000000000" remote="128569431000000000" testing="0" />
<file name="magenlinks.php" local="128569431600000000" remote="128569431600000000" testing="0" />
<file name="mainegenlinks.php" local="128569431600000000" remote="128569431600000000" testing="0" />
<file name="mapgenlinks.php" local="128569431600000000" remote="128569431600000000" testing="0" />
<file name="mdgenlinks.php" local="128569431600000000" remote="128569431600000000" testing="0" />
<file name="milgenlinks.php" local="128569431600000000" remote="128569431600000000" testing="0" />
<file name="mogenlinks.php" local="128569431600000000" remote="128569431600000000" testing="0" />
<file name="ncgenlinks.php" local="128569431600000000" remote="128569431600000000" testing="0" />
<file name="nhgenlinks.php" local="128569431600000000" remote="128569431600000000" testing="0" />
<file name="njgenlinks.php" local="128569431600000000" remote="128569431600000000" testing="0" />
<file name="nvgenlinks.php" local="128569431600000000" remote="128569431600000000" testing="0" />
<file name="othergenlinks.php" local="128569431600000000" remote="128569431600000000" testing="0" />
<file name="pagenlinks.php" local="128569431600000000" remote="128569431600000000" testing="0" />
<file name="sdgenlinks.php" local="128569431600000000" remote="128569431600000000" testing="0" />
<file name="tngenlinks.php" local="128569431600000000" remote="128569431600000000" testing="0" />
<file name="txgenlinks.php" local="128569431600000000" remote="128569431600000000" testing="0" />
<file name="utahgenlinks.php" local="128569431600000000" remote="128569431600000000" testing="0" />
<file name="vagenlinks.php" local="128569431600000000" remote="128569431600000000" testing="0" />
</dwsync>